AUTHORS
ChangeLog
LICENSE.txt
README.rst
setup.cfg
setup.py
puppetdb_api/__init__.py
puppetdb_api/puppetdb.py
puppetdb_api/query.py
puppetdb_api.egg-info/PKG-INFO
puppetdb_api.egg-info/SOURCES.txt
puppetdb_api.egg-info/dependency_links.txt
puppetdb_api.egg-info/top_level.txt
test/puppetdb_api_test.py