Metadata-Version: 1.1
Name: puppetdb-api
Version: 1.1-dev
Summary: Python wrapper for puppetDB API
Home-page: https://github.com/i-maravic/puppetdb-api
Author: Igor Maravić
Author-email: igor@spotify.com
License: Apache 2.0
Download-URL: https://github.com/i-maravic/puppetdb-api/tarball/1.1-dev
Platform: UNKNOWN
Classifier: Development Status :: 4 - Beta
Classifier: Intended Audience :: Developers
Classifier: Intended Audience :: Information Technology
Classifier: License :: OSI Approved :: Apache Software License
Classifier: Operating System :: OS Independent
Classifier: Programming Language :: Python
Classifier: Programming Language :: Python :: 2
Classifier: Programming Language :: Python :: 2.6
Classifier: Programming Language :: Python :: 2.7
Requires: requests
Requires: unittest2
Requires: httpmock
